ProxyPool/ProxyExceptions.py
ProxyPool/__init__.py
proxypool_util-0.1.4.dist-info/LICENCE
proxypool_util-0.1.4.dist-info/METADATA
proxypool_util-0.1.4.dist-info/WHEEL
proxypool_util-0.1.4.dist-info/top_level.txt
proxypool_util-0.1.4.dist-info/RECORD
