Metadata-Version: 2.1
Name: proxypool_util
Version: 0.1.4
Summary: Proxy pool to rotate and manage proxies
Author-email: Mykhailo Razbeiko <mykhailo.razb@gmail.com>
Project-URL: Homepage, https://github.com/MykhailoRp/proxypool_util
Project-URL: Issues, https://github.com/MykhailoRp/proxypool_util/issues
Classifier: Programming Language :: Python :: 3
Classifier: License :: OSI Approved :: MIT License
Classifier: Operating System :: OS Independent
Requires-Python: >=3.8
License-File: LICENCE
